componentes.v
`timescale 1 ns / 10 ps
module registro4 (input wire [3:0] entrada, input wire bit_en_desp, input wire Carga, Desplaza, clk, reset, output wire [3:0] salida);
	//Registro de 4 bits, soporta Carga de entrada, reseteo y desplazamiento aritmético o lógico
	// La línea de Carga indica que se va a asignar un nuevo valor al registro que viene por "entrada"
	// La línea de Desplaza indica que se va a desplazar el contenido del registro. El bit más significativo se completa con la entrada "bit_en_desp"

	assign enable = Carga | Desplaza; //Si se carga o desplaza se habilitan en modificación los biestables
	cdaff ff0(Carga, entrada[0], salida[1], clk, reset, enable, salida[0]);
	cdaff ff1(Carga, entrada[1], salida[2], clk, reset, enable, salida[1]);
	cdaff ff2(Carga, entrada[2], salida[3], clk, reset, enable, salida[2]);
	cdaff ff3(Carga, entrada[3], bit_en_desp, clk, reset, enable, salida[3]); //entra un bit en el desplaz
endmodule

module registro3 (input wire [2:0] entrada, input wire bit_en_desp, input wire Carga, Desplaza, clk, reset, output wire [2:0] salida);
	//Registro de 3 bits, soporta Carga de entrada, reseteo y desplazamiento aritmético o lógico
	// La línea de Carga indica que se va a asignar un nuevo valor al registro que viene por "entrada"
	// La línea de Desplaza indica que se va a desplazar el contenido del registro. El bit más significativo se completa con la entrada "bit_en_desp"

	assign enable = Carga | Desplaza; //Si se carga o desplaza se habilitan en modificación los biestables
	cdaff ff0(Carga, entrada[0], salida[1], clk, reset, enable, salida[0]);
	cdaff ff1(Carga, entrada[1], salida[2], clk, reset, enable, salida[1]);
	cdaff ff2(Carga, entrada[2], bit_en_desp, clk, reset, enable, salida[2]); //entra un bit en el desplaz
endmodule

//Biestable con entrada de mux para aceptar dos entradas posibles
module cdaff (input wire selc_d, inp_c, inp_d, clk, reset, carga, output wire salida);
	wire inp;
	
	ffdc ff0(clk, reset, carga, inp, salida);
	mux2_1_i1 mux0(inp, inp_d, inp_c, selc_d);
endmodule

//Mux de dos entradas de 1 bit realizado a partir de puertas 
module mux2_1_i1(output wire out, input wire a, b, s);
	//Declaración de conexiones internas
	wire  s_n, sa, sb;	   
	//Instancias de puertas y sus conexiones
	not inv1 (s_n, s);
	and and1 (sa, a, s_n);
	and and2 (sb, b, s);
	or or1 (out, sa, sb);
endmodule

module ffdc #(parameter retardo = 1)(input wire clk, reset, carga, d, output reg q);
	//reset asíncrono, carga síncrona
	always @(posedge clk, posedge reset)
	  if (reset)
		q <= #retardo 1'b0; //asignación no bloqueante q=0
	  else
		if (carga)
		  q <= #retardo d; //asignación no bloqueante q=d
endmodule

module sum_resta4(output wire[3:0] S, output wire c_out, input wire[3:0] A, input wire[3:0] B, input wire resta);
	assign {c_out, S} = (resta == 1) ? A - B : A + B;
endmodule

controlUnit.v
module controlUnit (input wire clk, start, input wire [1:0] q, output wire resta, desp, fin);

    // Cables
    // wire d3, d2, d1;
    // wire q0, q1, q2;

    wire [2:0] entrada, salida;

    // Biestables
    // ffdc D3 (clk, start, 1'b1, d3, q2);
    // ffdc D2 (clk, start, 1'b1, d2, q1);
    // ffdc D1 (clk, start, 1'b1, d1, q0);

    registro3 D(entrada, 1'b0, 1'b1, 1'b0, clk, start, salida);

    // assign entrada[1:0] = ~salida[1:0];

    // Entradas de los biestables
    // Negadas
    wire neg_q0, neg_q1, negQ0, neg_Q1, neg_Q2;

    assign neg_q0 = ~q[1];
    assign neg_q1 = ~q[0];
    assign neg_Q0 = ~salida[0];
    assign neg_Q1 = ~salida[1];
    assign neg_Q2 = ~salida[2];

    // Bits de la entrada del registro (D3, D2 y D1)
    assign entrada[2] = salida[2] | (salida[1] & (salida[0] | (neg_q0 & neg_q1))) | (q[1] & q[0]);
    assign entrada[1] = (salida[2] & salida[1]) | (neg_Q1 & (salida[0] | (neg_q0 & neg_q1) | (q[1] & q[0])) | (salida[1] & neg_Q0 & ((neg_q0 & q[0]) | (q[1] & neg_q1))));
    assign entrada[0] = (salida[2] & salida[1]) | (neg_Q0 & ((neg_q0 & q[0]) | (q[1] & neg_q1)));
    

    // // Salidas
    // // assign resta = (~q2 & ~q0 & q[1] & ~q[0]) | (~q1 & ~q0 & q[1] & ~q[0]);
    // // assign desp = (~q2 & q0) | (~q1 & q0) | (~q2 & ~q[1] & ~q[0]) | (~q1 & ~q[1] & ~q[0]) | (~q2 & q[1] & q[0]) | (~q1 & q[1] & q[0]);
    // // assign fin = q2 & q1;

    assign resta = neg_Q0 & q[1] & q[0] & (neg_Q2 | neg_Q1);
    assign desp = (salida[0] & (neg_Q2 | neg_Q1)) | (neg_q0 & neg_q1 & (neg_Q2 | neg_Q1)) | (q[1] & q[0] & (neg_Q2 | neg_Q1));
    assign fin = salida[2] & salida[1];

    // // Resta
    // wire R_forAnd21, R_forAnd31, R_forAnd32;

    // or R_or1(neg_Q2, neg_Q1, R_forAnd32);

    // and R_and1(neg_Q0, q[1], R_forAnd21);

    // and R_and2(R_forAnd21, neg_q1, R_forAnd31);
    // and R_and3(R_forAnd31, R_forAnd32, resta);

    // // Desplazamiento
    // wire sum_neg_21, D_forOr11, D_forAnd31, D_forOr12, D_forOr21;
    // wire D_forAnd51, D_forOr22;

    // or D_sum_neg_21(neg_Q2, neg_Q1, sum_neg_21);

    // and D_and1(salida[0], sum_neg_21, D_forOr11);
    // and D_and2(neg_q0, neg_q1, D_forAnd31);
    // and D_and3(D_forAnd31, sum_neg_21, D_forOr12);

    // or D_or1(D_forOr11, D_forOr12, D_forOr21);

    // and D_and4(q[1], q[0], D_forAnd51);
    // and D_and5(D_forAnd51, sum_neg_21, D_forOr22);

    // or D_or2(D_forOr21, D_forOr22, desp);

    // // FIN
    // and fin_and(salida[2], salida[1], fin);

endmodule

datapath.v
module datapath (input wire [2:0] multiplicador, multiplicando, input wire start, clk, resta, desp, output wire [1:0] q, output wire [5:0] resultado);

    // Cables
    wire [3:0] a_to_sumador, m_to_sumador, q_value;
    wire [3:0] entrada_Q, entrada_M, entrada_A;
    
    // Cable 'basura' para el overflow
    wire aux;

    // Valores a 4 bits
    // assign entrada_A = 4'b0;
    assign entrada_Q = {multiplicador, 1'b0}; // entrada_Q[0] corresponde a q(-1), mientras que entrada_Q[1] corresponde a q(0)
    assign entrada_M = {multiplicando[2], multiplicando};

    // Registros
    registro4 A(entrada_A, entrada_A[3], 1'b1, desp, clk, start, a_to_sumador);
    registro4 Q(entrada_Q, entrada_A[0], start, desp, clk, 1'b0, q_value);
    registro4 M(entrada_M, 1'b0, 1'b1, 1'b0, clk, start, m_to_sumador);

    // Sumador
    sum_resta4 sumador(entrada_A, aux, a_to_sumador, m_to_sumador, resta);

    // Salidas
    assign resultado = {a_to_sumador, q_value};

    assign q = {entrada_Q[1], entrada_Q[0]};

endmodule

multiplicador.v
`timescale 1 ns / 10 ps
module multiplicador (input wire [2:0] multiplicador, multiplicando, input wire clk, start, output wire [5:0] resultado, output wire fin);
  
  // Cables de interconexion
  wire sub, desp;
  wire [1:0] q;

  // Camino de datos
  // Le pasamos al camino de datos las señales de control proporcionadas por la unidad de control
  // También le pasamos el multiplicador, el multiplicando, y CLK
  datapath dp(multiplicador, multiplicando, start, clk, sub, desp, q, resultado);
  
  // La UC va a recibir el CLK y posiblemente la señal de start, asi como proporcionar la señal de FIN
  // Tambien recibira q0 y q-1 del camino de datos
  controlUnit uc(clk, start, q, sub, desp, fin);
  
endmodule

multiplicador_tb.v
`timescale 1 ns / 10 ps
module multiplicador_tb;
//Recordar que el caso de -4 en tres bits en el multiplicando dará error en Booth si no hacemos que los registros A y M tengan un bit más (hay overflow) (depende de la implementación del sumador/restador)
parameter NUM_BITS = 3;
parameter NUM_TESTS = (2**(2*NUM_BITS));
parameter MAX_RANGE = (2**(NUM_BITS-1))-1;
parameter MIN_RANGE = - (2**(NUM_BITS-1));
integer contador;
reg clk, start;
wire Fin;
reg signed [NUM_BITS-1:0] multiplicador;
reg signed [NUM_BITS-1:0] multiplicando;
wire [(2*NUM_BITS)-1:0] resultado;
reg signed [(2*NUM_BITS)-1:0] resultado_esperado;

// generación de reloj clk
always //siempre activo, no hay condición de activación
begin
  clk = 1'b0;
  #5;
  clk = 1'b1;
  #5;
end

// Módulo a probar
multiplicador mult(multiplicador, multiplicando, clk, start, resultado, Fin);

initial
begin
  $dumpfile("multiplicador_tb.vcd");
  $dumpvars;
  #10000   //Evita ejecución infinita
  $finish;
end

//Preparación caso inicial
initial
begin
  multiplicando = MIN_RANGE;
  multiplicador = MIN_RANGE;
  contador = 1;
end 

initial
begin
  start = 1'b1;
  #1;
  start = 1'b0;
end

always @(posedge Fin)
begin
  resultado_esperado = multiplicador * multiplicando;
  //Comprobación de resultados
  $write("%d x %d = %d", multiplicando, multiplicador, resultado_esperado);
  if (resultado !== resultado_esperado)
    $display("\tERROR    Obtenido=%b", resultado);
  else
    $display("\tCORRECTO Obtenido=%b", resultado);
  
  #20  //tiempo de espera entre una multiplicación y la siguiente
  if (contador == NUM_TESTS)
    $finish;
  else //Siguiente caso
  begin
    contador = contador + 1;
    if (multiplicador == MAX_RANGE)
    begin
      multiplicador = MIN_RANGE;
      multiplicando = multiplicando + 1;
    end
    else
    begin
      multiplicador = multiplicador + 1;
    end
    start = 1'b1;
    #1;
    start = 1'b0;           
  end
end

endmodule

multiplicador_tb.vcd
$date
	Fri Feb  7 12:28:06 2020
$end
$version
	Icarus Verilog
$end
$timescale
	10ps
$end
$scope module multiplicador_tb $end
$var wire 6 ! resultado [5:0] $end
$var wire 1 " Fin $end
$var reg 1 # clk $end
$var reg 3 $ multiplicador [2:0] $end
$var reg 3 % multiplicando [2:0] $end
$var reg 6 & resultado_esperado [5:0] $end
$var reg 1 ' start $end
$var integer 32 ( contador [31:0] $end
$scope module mult $end
$var wire 1 # clk $end
$var wire 3 ) multiplicador [2:0] $end
$var wire 3 * multiplicando [2:0] $end
$var wire 1 ' start $end
$var wire 1 + sub $end
$var wire 6 , resultado [5:0] $end
$var wire 2 - q [1:0] $end
$var wire 1 " fin $end
$var wire 1 . desp $end
$scope module dp $end
$var wire 1 # clk $end
$var wire 3 / multiplicador [2:0] $end
$var wire 3 0 multiplicando [2:0] $end
$var wire 1 ' start $end
$var wire 6 1 resultado [5:0] $end
$var wire 1 + resta $end
$var wire 4 2 q_value [3:0] $end
$var wire 2 3 q [1:0] $end
$var wire 4 4 m_to_sumador [3:0] $end
$var wire 4 5 entrada_Q [3:0] $end
$var wire 4 6 entrada_M [3:0] $end
$var wire 4 7 entrada_A [3:0] $end
$var wire 1 . desp $end
$var wire 1 8 aux $end
$var wire 4 9 a_to_sumador [3:0] $end
$scope module A $end
$var wire 1 : Carga $end
$var wire 1 ; bit_en_desp $end
$var wire 1 # clk $end
$var wire 1 < enable $end
$var wire 1 ' reset $end
$var wire 4 = salida [3:0] $end
$var wire 4 > entrada [3:0] $end
$var wire 1 . Desplaza $end
$scope module ff0 $end
$var wire 1 < carga $end
$var wire 1 # clk $end
$var wire 1 ? inp_c $end
$var wire 1 @ inp_d $end
$var wire 1 ' reset $end
$var wire 1 : selc_d $end
$var wire 1 A salida $end
$var wire 1 B inp $end
$scope module ff0 $end
$var wire 1 < carga $end
$var wire 1 # clk $end
$var wire 1 ' reset $end
$var wire 1 B d $end
$var reg 1 A q $end
$upscope $end
$scope module mux0 $end
$var wire 1 @ a $end
$var wire 1 ? b $end
$var wire 1 B out $end
$var wire 1 : s $end
$var wire 1 C s_n $end
$var wire 1 D sa $end
$var wire 1 E sb $end
$upscope $end
$upscope $end
$scope module ff1 $end
$var wire 1 < carga $end
$var wire 1 # clk $end
$var wire 1 F inp_c $end
$var wire 1 G inp_d $end
$var wire 1 ' reset $end
$var wire 1 : selc_d $end
$var wire 1 H salida $end
$var wire 1 I inp $end
$scope module ff0 $end
$var wire 1 < carga $end
$var wire 1 # clk $end
$var wire 1 ' reset $end
$var wire 1 I d $end
$var reg 1 H q $end
$upscope $end
$scope module mux0 $end
$var wire 1 G a $end
$var wire 1 F b $end
$var wire 1 I out $end
$var wire 1 : s $end
$var wire 1 J s_n $end
$var wire 1 K sa $end
$var wire 1 L sb $end
$upscope $end
$upscope $end
$scope module ff2 $end
$var wire 1 < carga $end
$var wire 1 # clk $end
$var wire 1 M inp_c $end
$var wire 1 N inp_d $end
$var wire 1 ' reset $end
$var wire 1 : selc_d $end
$var wire 1 O salida $end
$var wire 1 P inp $end
$scope module ff0 $end
$var wire 1 < carga $end
$var wire 1 # clk $end
$var wire 1 ' reset $end
$var wire 1 P d $end
$var reg 1 O q $end
$upscope $end
$scope module mux0 $end
$var wire 1 N a $end
$var wire 1 M b $end
$var wire 1 P out $end
$var wire 1 : s $end
$var wire 1 Q s_n $end
$var wire 1 R sa $end
$var wire 1 S sb $end
$upscope $end
$upscope $end
$scope module ff3 $end
$var wire 1 < carga $end
$var wire 1 # clk $end
$var wire 1 T inp_c $end
$var wire 1 ; inp_d $end
$var wire 1 ' reset $end
$var wire 1 : selc_d $end
$var wire 1 U salida $end
$var wire 1 V inp $end
$scope module ff0 $end
$var wire 1 < carga $end
$var wire 1 # clk $end
$var wire 1 ' reset $end
$var wire 1 V d $end
$var reg 1 U q $end
$upscope $end
$scope module mux0 $end
$var wire 1 ; a $end
$var wire 1 T b $end
$var wire 1 V out $end
$var wire 1 : s $end
$var wire 1 W s_n $end
$var wire 1 X sa $end
$var wire 1 Y sb $end
$upscope $end
$upscope $end
$upscope $end
$scope module M $end
$var wire 1 Z Carga $end
$var wire 1 [ Desplaza $end
$var wire 1 \ bit_en_desp $end
$var wire 1 # clk $end
$var wire 1 ] enable $end
$var wire 4 ^ entrada [3:0] $end
$var wire 1 ' reset $end
$var wire 4 _ salida [3:0] $end
$scope module ff0 $end
$var wire 1 ] carga $end
$var wire 1 # clk $end
$var wire 1 ` inp_c $end
$var wire 1 a inp_d $end
$var wire 1 ' reset $end
$var wire 1 Z selc_d $end
$var wire 1 b salida $end
$var wire 1 c inp $end
$scope module ff0 $end
$var wire 1 ] carga $end
$var wire 1 # clk $end
$var wire 1 ' reset $end
$var wire 1 c d $end
$var reg 1 b q $end
$upscope $end
$scope module mux0 $end
$var wire 1 a a $end
$var wire 1 ` b $end
$var wire 1 c out $end
$var wire 1 Z s $end
$var wire 1 d s_n $end
$var wire 1 e sa $end
$var wire 1 f sb $end
$upscope $end
$upscope $end
$scope module ff1 $end
$var wire 1 ] carga $end
$var wire 1 # clk $end
$var wire 1 g inp_c $end
$var wire 1 h inp_d $end
$var wire 1 ' reset $end
$var wire 1 Z selc_d $end
$var wire 1 i salida $end
$var wire 1 j inp $end
$scope module ff0 $end
$var wire 1 ] carga $end
$var wire 1 # clk $end
$var wire 1 ' reset $end
$var wire 1 j d $end
$var reg 1 i q $end
$upscope $end
$scope module mux0 $end
$var wire 1 h a $end
$var wire 1 g b $end
$var wire 1 j out $end
$var wire 1 Z s $end
$var wire 1 k s_n $end
$var wire 1 l sa $end
$var wire 1 m sb $end
$upscope $end
$upscope $end
$scope module ff2 $end
$var wire 1 ] carga $end
$var wire 1 # clk $end
$var wire 1 n inp_c $end
$var wire 1 o inp_d $end
$var wire 1 ' reset $end
$var wire 1 Z selc_d $end
$var wire 1 p salida $end
$var wire 1 q inp $end
$scope module ff0 $end
$var wire 1 ] carga $end
$var wire 1 # clk $end
$var wire 1 ' reset $end
$var wire 1 q d $end
$var reg 1 p q $end
$upscope $end
$scope module mux0 $end
$var wire 1 o a $end
$var wire 1 n b $end
$var wire 1 q out $end
$var wire 1 Z s $end
$var wire 1 r s_n $end
$var wire 1 s sa $end
$var wire 1 t sb $end
$upscope $end
$upscope $end
$scope module ff3 $end
$var wire 1 ] carga $end
$var wire 1 # clk $end
$var wire 1 u inp_c $end
$var wire 1 \ inp_d $end
$var wire 1 ' reset $end
$var wire 1 Z selc_d $end
$var wire 1 v salida $end
$var wire 1 w inp $end
$scope module ff0 $end
$var wire 1 ] carga $end
$var wire 1 # clk $end
$var wire 1 ' reset $end
$var wire 1 w d $end
$var reg 1 v q $end
$upscope $end
$scope module mux0 $end
$var wire 1 \ a $end
$var wire 1 u b $end
$var wire 1 w out $end
$var wire 1 Z s $end
$var wire 1 x s_n $end
$var wire 1 y sa $end
$var wire 1 z sb $end
$upscope $end
$upscope $end
$upscope $end
$scope module Q $end
$var wire 1 ' Carga $end
$var wire 1 { bit_en_desp $end
$var wire 1 # clk $end
$var wire 1 | enable $end
$var wire 4 } entrada [3:0] $end
$var wire 1 ~ reset $end
$var wire 4 !" salida [3:0] $end
$var wire 1 . Desplaza $end
$scope module ff0 $end
$var wire 1 | carga $end
$var wire 1 # clk $end
$var wire 1 "" inp_c $end
$var wire 1 #" inp_d $end
$var wire 1 ~ reset $end
$var wire 1 ' selc_d $end
$var wire 1 $" salida $end
$var wire 1 %" inp $end
$scope module ff0 $end
$var wire 1 | carga $end
$var wire 1 # clk $end
$var wire 1 ~ reset $end
$var wire 1 %" d $end
$var reg 1 $" q $end
$upscope $end
$scope module mux0 $end
$var wire 1 #" a $end
$var wire 1 "" b $end
$var wire 1 %" out $end
$var wire 1 ' s $end
$var wire 1 &" s_n $end
$var wire 1 '" sa $end
$var wire 1 (" sb $end
$upscope $end
$upscope $end
$scope module ff1 $end
$var wire 1 | carga $end
$var wire 1 # clk $end
$var wire 1 )" inp_c $end
$var wire 1 *" inp_d $end
$var wire 1 ~ reset $end
$var wire 1 ' selc_d $end
$var wire 1 +" salida $end
$var wire 1 ," inp $end
$scope module ff0 $end
$var wire 1 | carga $end
$var wire 1 # clk $end
$var wire 1 ~ reset $end
$var wire 1 ," d $end
$var reg 1 +" q $end
$upscope $end
$scope module mux0 $end
$var wire 1 *" a $end
$var wire 1 )" b $end
$var wire 1 ," out $end
$var wire 1 ' s $end
$var wire 1 -" s_n $end
$var wire 1 ." sa $end
$var wire 1 /" sb $end
$upscope $end
$upscope $end
$scope module ff2 $end
$var wire 1 | carga $end
$var wire 1 # clk $end
$var wire 1 0" inp_c $end
$var wire 1 1" inp_d $end
$var wire 1 ~ reset $end
$var wire 1 ' selc_d $end
$var wire 1 2" salida $end
$var wire 1 3" inp $end
$scope module ff0 $end
$var wire 1 | carga $end
$var wire 1 # clk $end
$var wire 1 ~ reset $end
$var wire 1 3" d $end
$var reg 1 2" q $end
$upscope $end
$scope module mux0 $end
$var wire 1 1" a $end
$var wire 1 0" b $end
$var wire 1 3" out $end
$var wire 1 ' s $end
$var wire 1 4" s_n $end
$var wire 1 5" sa $end
$var wire 1 6" sb $end
$upscope $end
$upscope $end
$scope module ff3 $end
$var wire 1 | carga $end
$var wire 1 # clk $end
$var wire 1 7" inp_c $end
$var wire 1 { inp_d $end
$var wire 1 ~ reset $end
$var wire 1 ' selc_d $end
$var wire 1 8" salida $end
$var wire 1 9" inp $end
$scope module ff0 $end
$var wire 1 | carga $end
$var wire 1 # clk $end
$var wire 1 ~ reset $end
$var wire 1 9" d $end
$var reg 1 8" q $end
$upscope $end
$scope module mux0 $end
$var wire 1 { a $end
$var wire 1 7" b $end
$var wire 1 9" out $end
$var wire 1 ' s $end
$var wire 1 :" s_n $end
$var wire 1 ;" sa $end
$var wire 1 <" sb $end
$upscope $end
$upscope $end
$upscope $end
$scope module sumador $end
$var wire 4 =" A [3:0] $end
$var wire 4 >" B [3:0] $end
$var wire 1 + resta $end
$var wire 1 8 c_out $end
$var wire 4 ?" S [3:0] $end
$upscope $end
$upscope $end
$scope module uc $end
$var wire 1 # clk $end
$var wire 1 . desp $end
$var wire 1 " fin $end
$var wire 1 @" neg_Q0 $end
$var wire 1 A" neg_Q1 $end
$var wire 1 B" neg_Q2 $end
$var wire 1 C" neg_q0 $end
$var wire 1 D" neg_q1 $end
$var wire 2 E" q [1:0] $end
$var wire 1 + resta $end
$var wire 1 ' start $end
$var wire 3 F" salida [2:0] $end
$var wire 3 G" entrada [2:0] $end
$scope module D $end
$var wire 1 H" Carga $end
$var wire 1 I" Desplaza $end
$var wire 1 J" bit_en_desp $end
$var wire 1 # clk $end
$var wire 1 K" enable $end
$var wire 3 L" entrada [2:0] $end
$var wire 1 ' reset $end
$var wire 3 M" salida [2:0] $end
$scope module ff0 $end
$var wire 1 K" carga $end
$var wire 1 # clk $end
$var wire 1 N" inp_c $end
$var wire 1 O" inp_d $end
$var wire 1 ' reset $end
$var wire 1 H" selc_d $end
$var wire 1 P" salida $end
$var wire 1 Q" inp $end
$scope module ff0 $end
$var wire 1 K" carga $end
$var wire 1 # clk $end
$var wire 1 ' reset $end
$var wire 1 Q" d $end
$var reg 1 P" q $end
$upscope $end
$scope module mux0 $end
$var wire 1 O" a $end
$var wire 1 N" b $end
$var wire 1 Q" out $end
$var wire 1 H" s $end
$var wire 1 R" s_n $end
$var wire 1 S" sa $end
$var wire 1 T" sb $end
$upscope $end
$upscope $end
$scope module ff1 $end
$var wire 1 K" carga $end
$var wire 1 # clk $end
$var wire 1 U" inp_c $end
$var wire 1 V" inp_d $end
$var wire 1 ' reset $end
$var wire 1 H" selc_d $end
$var wire 1 W" salida $end
$var wire 1 X" inp $end
$scope module ff0 $end
$var wire 1 K" carga $end
$var wire 1 # clk $end
$var wire 1 ' reset $end
$var wire 1 X" d $end
$var reg 1 W" q $end
$upscope $end
$scope module mux0 $end
$var wire 1 V" a $end
$var wire 1 U" b $end
$var wire 1 X" out $end
$var wire 1 H" s $end
$var wire 1 Y" s_n $end
$var wire 1 Z" sa $end
$var wire 1 [" sb $end
$upscope $end
$upscope $end
$scope module ff2 $end
$var wire 1 K" carga $end
$var wire 1 # clk $end
$var wire 1 \" inp_c $end
$var wire 1 J" inp_d $end
$var wire 1 ' reset $end
$var wire 1 H" selc_d $end
$var wire 1 ]" salida $end
$var wire 1 ^" inp $end
$scope module ff0 $end
$var wire 1 K" carga $end
$var wire 1 # clk $end
$var wire 1 ' reset $end
$var wire 1 ^" d $end
$var reg 1 ]" q $end
$upscope $end
$scope module mux0 $end
$var wire 1 J" a $end
$var wire 1 \" b $end
$var wire 1 ^" out $end
$var wire 1 H" s $end
$var wire 1 _" s_n $end
$var wire 1 `" sa $end
$var wire 1 a" sb $end
$upscope $end
$upscope $end
$upscope $end
$upscope $end
$upscope $end
$upscope $end
$enddefinitions $end
#0
$dumpvars
xa"
0`"
0_"
x^"
x]"
x\"
x["
0Z"
0Y"
xX"
xW"
xV"
xU"
xT"
0S"
0R"
xQ"
xP"
xO"
xN"
bx M"
bx L"
1K"
0J"
0I"
1H"
bx G"
bx F"
b0 E"
1D"
1C"
xB"
xA"
x@"
bx ?"
bx >"
bx ="
1<"
0;"
0:"
19"
x8"
17"
06"
05"
04"
03"
x2"
x1"
00"
0/"
0."
0-"
0,"
x+"
x*"
0)"
0("
0'"
0&"
0%"
x$"
x#"
0""
bx !"
0~
b1000 }
1|
x{
1z
0y
0x
1w
xv
1u
1t
0s
0r
1q
xp
xo
1n
0m
0l
0k
0j
xi
xh
0g
0f
0e
0d
0c
xb
xa
0`
bx _
b1100 ^
1]
0\
0[
1Z
xY
0X
0W
xV
xU
xT
xS
0R
0Q
xP
xO
xN
xM
xL
0K
0J
xI
xH
xG
xF
xE
0D
0C
xB
xA
x@
x?
bx >
bx =
1<
x;
1:
bx 9
x8
bx 7
b1100 6
b1000 5
bx 4
b0 3
bx 2
bx 1
b100 0
b100 /
x.
b0 -
bx ,
0+
b100 *
b100 )
b1 (
1'
bx &
b100 %
b100 $
0#
x"
bx !
$end
#100
1X"
0^"
1["
0a"
1U"
0Q"
1.
0V
0P
0I
0B
0\"
0T"
0Y
0S
0L
0E
0N"
0T
0M
0F
0?
0{
0;
b10 G"
b10 L"
b0 7
b0 >
b0 ?"
08
1@"
1A"
0"
1B"
0@
b0xxxx !
b0xxxx ,
b0xxxx 1
0G
0N
0a
0h
0o
0O"
0V"
0A
0H
0O
b0 9
b0 =
b0 ="
0U
0b
0i
0p
b0 4
b0 _
b0 >"
0v
0P"
0W"
b0 F"
b0 M"
0]"
x%"
x,"
x3"
x'"
x."
x5"
0;"
09"
1|
1&"
1-"
14"
1:"
0<"
0'
#500
1#
#600
0X"
1^"
0["
1a"
0U"
1\"
1V
1P
b100 G"
b100 L"
1Y
1S
1T
1M
1;
03"
0A"
b1100 7
b1100 >
b1100 ?"
05"
1O"
1o
1h
01"
b0xxx !
b0xxx ,
b0xxx 1
b10 F"
b10 M"
1W"
1v
b1100 4
b1100 _
b1100 >"
1p
b0xxx 2
b0xxx !"
08"
#1000
0#
#1500
1#
#1600
1X"
1["
1U"
0P
b110 G"
b110 L"
0S
0M
0,"
b1000 7
b1000 >
b1000 ?"
18
1A"
0B"
0."
1G
1N
0O"
1V"
0*"
b0xx !
b0xx ,
b0xx 1
1O
b1100 9
b1100 =
b1100 ="
1U
0W"
b100 F"
b100 M"
1]"
b0xx 2
b0xx !"
02"
#2000
0#
#2500
1#
#2600
0|
1Q"
0.
1T"
0V
1P
1N"
0Y
1S
b10000 &
b111 G"
b111 L"
0T
1M
0;
0%"
1"
0A"
b100 7
b100 >
b100 ?"
0'"
1O"
0G
0#"
b0x !
b0x ,
b0x 1
b110 F"
b110 M"
1W"
b1000 9
b1000 =
b1000 ="
0O
b0x 2
b0x !"
0+"
#3000
0#
#3500
1#
#3600
0P
0S
0M
b0 7
b0 >
b0 ?"
0@"
1G
0N
1O
b100 9
b100 =
b100 ="
0U
b111 F"
b111 M"
1P"
#4000
0#
#4500
1#
#4600
1V
1P
1Y
1S
1T
1M
1;
b1100 7
b1100 >
b1100 ?"
08
0G
b0 9
b0 =
b0 ="
0O
0C"
1,"
19"
1|
0&"
0-"
1/"
04"
0:"
1<"
b10 -
b10 3
b10 E"
1)"
1'
b1010 5
b1010 }
b101 $
b101 )
b101 /
b10 (
#4700
0^"
0a"
1Q"
0X"
0V
0P
0\"
1T"
0["
0Y
0S
1N"
0U"
0T
0M
0;
b1 G"
b1 L"
b0 7
b0 >
b0 ?"
1@"
1A"
0"
1B"
0h
0o
0O"
0V"
0p
b0 4
b0 _
b0 >"
0v
0P"
0W"
b0 F"
b0 M"
0]"
0,"
09"
0|
1&"
1-"
0/"
14"
1:"
0<"
0'
#5000
0#
#5500
1#
#5600
1X"
1["
1U"
0Q"
0T"
1|
0N"
1V
1P
1.
b10 G"
b10 L"
1Y
1S
1T
1M
1;
0@"
b1100 7
b1100 >
b1100 ?"
1o
1h
b1 F"
b1 M"
1P"
1v
b1100 4
b1100 _
b1100 >"
1p
#6000
0#
#6500
1#
#6600
1X"
1Q"
0^"
1["
1T"
0a"
1U"
0P
0|
1N"
0\"
0S
0.
b11 G"
b11 L"
0M
b1000 7
b1000 >
b1000 ?"
18
1@"
0A"
1G
1N
1O"
b0 !
b0 ,
b0 1
1O
b1100 9
b1100 =
b1100 ="
1U
0P"
b10 F"
b10 M"
1W"
b0 2
b0 !"
0$"
#7000
0#
#7500
1#
#7600
0X"
1^"
0["
1a"
0U"
0Q"
1\"
0T"
1|
0N"
0V
1P
1.
b100 G"
b100 L"
0Y
1S
0T
1M
0;
0@"
b100 7
b100 >
b100 ?"
0G
b11 F"
b11 M"
1P"
b1000 9
b1000 =
b1000 ="
0O
#8000
0#
#8500
1#
#8600
0X"
1Q"
0["
1T"
0U"
0P
0|
1N"
0S
0.
b101 G"
b101 L"
0M
b0 7
b0 >
b0 ?"
1@"
1A"
0B"
1G
0N
0O"
1V"
1O
b100 9
b100 =
b100 ="
0U
0P"
0W"
b100 F"
b100 M"
1]"
#9000
0#
#9500
1#
#9600
1X"
1["
1U"
0Q"
0T"
1|
0N"
1V
1P
1.
b110 G"
b110 L"
1Y
1S
1T
1M
1;
0@"
b1100 7
b1100 >
b1100 ?"
08
0G
b101 F"
b101 M"
1P"
b0 9
b0 =
b0 ="
0O
#10000
0#
#10500
1#
#10600
1Q"
0P
0|
1T"
0S
0.
1N"
0M
b1100 &
b111 G"
b111 L"
b1000 7
b1000 >
b1000 ?"
18
1@"
1"
0A"
1G
1N
1O"
1O
b1100 9
b1100 =
b1100 ="
1U
0P"
b110 F"
b110 M"
1W"
#11000
0#
#11500
1#
#11600
0V
1P
0Y
1S
0T
1M
0;
0@"
b100 7
b100 >
b100 ?"
0G
b111 F"
b111 M"
1P"
b1000 9
b1000 =
b1000 ="
0O
#12000
0#
#12500
1#
#12600
0P
0S
0M
b0 7
b0 >
b0 ?"
1G
0N
1O
b100 9
b100 =
b100 ="
0U
1C"
13"
19"
1|
0&"
0-"
04"
16"
0:"
1<"
b0 -
b0 3
b0 E"
0)"
10"
1'
b1100 5
b1100 }
b110 $
b110 )
b110 /
b11 (
#12700
0^"
0Q"
1X"
1.
0a"
0T"
1["
0\"
0N"
1U"
b10 G"
b10 L"
1B"
0"
1A"
1@"
08
0V"
0O"
0o
0h
0G
0]"
0W"
b0 F"
b0 M"
0P"
0v
b0 4
b0 _
b0 >"
0p
b0 9
b0 =
b0 ="
0O
03"
09"
1|
1&"
1-"
14"
06"
1:"
0<"
0'
#13000
0#
#13500
1#
#13600
0X"
1^"
0["
1a"
0U"
1V
1P
1\"
1Y
1S
b100 G"
b100 L"
1T
1M
1;
b1100 7
b1100 >
b1100 ?"
0A"
1h
1o
1O"
1p
b1100 4
b1100 _
b1100 >"
1v
b10 F"
b10 M"
1W"
#14000
0#
#14500
1#
#14600
1X"
1["
1U"
b110 G"
b110 L"
0P
0S
0M
0B"
1A"
b1000 7
b1000 >
b1000 ?"
18
1V"
0O"
1N
1G
1]"
b100 F"
b100 M"
0W"
1U
b1100 9
b1100 =
b1100 ="
1O
#15000
0#
#15500
1#
#15600
0|
1Q"
0.
0V
1P
1T"
0Y
1S
1N"
0T
1M
0;
b1000 &
b111 G"
b111 L"
b100 7
b100 >
b100 ?"
1"
0A"
0G
1O"
b1000 9
b1000 =
b1000 ="
0O
b110 F"
b110 M"
1W"
#16000
0#
#16500
1#
